{
  "minecraft:recipes/building_blocks/pink_concrete_powder": {
    "criteria": {
      "has_sand": "2022-09-23 21:23:53 +0000"
    },
    "done": true
  },
  "minecraft:recipes/building_blocks/red_concrete_powder": {
    "criteria": {
      "has_sand": "2022-09-23 21:23:53 +0000"
    },
    "done": true
  },
  "minecraft:recipes/misc/emerald": {
    "criteria": {
      "has_emerald_block": "2022-10-02 13:10:33 +0000"
    },
    "done": true
  },
  "minecraft:recipes/tools/compass": {
    "criteria": {
      "has_redstone": "2022-08-21 18:33:30 +0000"
    },
    "done": true
  },
  "minecraft:recipes/building_blocks/purple_concrete_powder": {
    "criteria": {
      "has_sand": "2022-09-23 21:23:53 +0000"
    },
    "done": true
  },
  "minecraft:recipes/building_blocks/magenta_concrete_powder": {
    "criteria": {
      "has_sand": "2022-09-23 21:23:53 +0000"
    },
    "done": true
  },
  "minecraft:recipes/decorations/iron_bars": {
    "criteria": {
      "has_iron_ingot": "2022-09-19 14:31:29 +0000"
    },
    "done": true
  },
  "minecraft:recipes/combat/iron_sword": {
    "criteria": {
      "has_iron_ingot": "2022-09-19 14:31:29 +0000"
    },
    "done": true
  },
  "minecraft:recipes/building_blocks/lime_concrete_powder": {
    "criteria": {
      "has_sand": "2022-09-23 21:23:53 +0000"
    },
    "done": true
  },
  "minecraft:recipes/redstone/target": {
    "criteria": {
      "has_redstone": "2022-08-21 18:33:30 +0000"
    },
    "done": true
  },
  "minecraft:recipes/tools/iron_pickaxe": {
    "criteria": {
      "has_iron_ingot": "2022-09-19 14:31:29 +0000"
    },
    "done": true
  },
  "minecraft:recipes/transportation/minecart": {
    "criteria": {
      "has_iron_ingot": "2022-09-19 14:31:29 +0000"
    },
    "done": true
  },
  "minecraft:recipes/building_blocks/yellow_concrete_powder": {
    "criteria": {
      "has_sand": "2022-09-23 21:23:53 +0000"
    },
    "done": true
  },
  "minecraft:adventure/adventuring_time": {
    "criteria": {
      "minecraft:plains": "2022-08-19 12:36:03 +0000"
    },
    "done": false
  },
  "minecraft:recipes/redstone/iron_door": {
    "criteria": {
      "has_iron_ingot": "2022-09-19 14:31:29 +0000"
    },
    "done": true
  },
  "minecraft:recipes/building_blocks/sandstone": {
    "criteria": {
      "has_sand": "2022-09-23 21:23:53 +0000"
    },
    "done": true
  },
  "minecraft:recipes/tools/iron_hoe": {
    "criteria": {
      "has_iron_ingot": "2022-09-19 14:31:29 +0000"
    },
    "done": true
  },
  "minecraft:recipes/redstone/redstone_torch": {
    "criteria": {
      "has_redstone": "2022-08-21 18:33:30 +0000"
    },
    "done": true
  },
  "minecraft:recipes/misc/iron_nugget": {
    "criteria": {
      "has_iron_ingot": "2022-09-19 14:31:29 +0000"
    },
    "done": true
  },
  "minecraft:recipes/decorations/chest": {
    "criteria": {
      "has_lots_of_items": "2022-08-21 03:03:08 +0000"
    },
    "done": true
  },
  "minecraft:end/elytra": {
    "criteria": {
      "elytra": "2022-09-19 14:37:12 +0000"
    },
    "done": true
  },
  "minecraft:recipes/building_blocks/brown_concrete_powder": {
    "criteria": {
      "has_sand": "2022-09-23 21:23:53 +0000"
    },
    "done": true
  },
  "minecraft:recipes/building_blocks/iron_block": {
    "criteria": {
      "has_iron_ingot": "2022-09-19 14:31:29 +0000"
    },
    "done": true
  },
  "minecraft:recipes/building_blocks/green_concrete_powder": {
    "criteria": {
      "has_sand": "2022-09-23 21:23:53 +0000"
    },
    "done": true
  },
  "minecraft:recipes/misc/red_dye_from_poppy": {
    "criteria": {
      "has_poppy": "2022-09-19 14:31:39 +0000"
    },
    "done": true
  },
  "minecraft:recipes/tools/iron_shovel": {
    "criteria": {
      "has_iron_ingot": "2022-09-19 14:31:29 +0000"
    },
    "done": true
  },
  "minecraft:recipes/redstone/iron_trapdoor": {
    "criteria": {
      "has_iron_ingot": "2022-09-19 14:31:29 +0000"
    },
    "done": true
  },
  "minecraft:recipes/decorations/smithing_table": {
    "criteria": {
      "has_iron_ingot": "2022-09-19 14:31:29 +0000"
    },
    "done": true
  },
  "minecraft:recipes/tools/shears": {
    "criteria": {
      "has_iron_ingot": "2022-09-19 14:31:29 +0000"
    },
    "done": true
  },
  "minecraft:adventure/root": {
    "criteria": {
      "killed_something": "2022-09-19 14:31:29 +0000"
    },
    "done": true
  },
  "minecraft:recipes/building_blocks/white_concrete_powder": {
    "criteria": {
      "has_sand": "2022-09-23 21:23:53 +0000"
    },
    "done": true
  },
  "minecraft:recipes/redstone/heavy_weighted_pressure_plate": {
    "criteria": {
      "has_iron_ingot": "2022-09-19 14:31:29 +0000"
    },
    "done": true
  },
  "minecraft:recipes/building_blocks/blue_concrete_powder": {
    "criteria": {
      "has_sand": "2022-09-23 21:23:53 +0000"
    },
    "done": true
  },
  "minecraft:recipes/tools/clock": {
    "criteria": {
      "has_redstone": "2022-08-21 18:33:30 +0000"
    },
    "done": true
  },
  "minecraft:recipes/building_blocks/gray_concrete_powder": {
    "criteria": {
      "has_sand": "2022-09-23 21:23:53 +0000"
    },
    "done": true
  },
  "minecraft:recipes/combat/iron_leggings": {
    "criteria": {
      "has_iron_ingot": "2022-09-19 14:31:29 +0000"
    },
    "done": true
  },
  "minecraft:recipes/redstone/redstone_block": {
    "criteria": {
      "has_redstone": "2022-08-21 18:33:30 +0000"
    },
    "done": true
  },
  "minecraft:recipes/tools/iron_axe": {
    "criteria": {
      "has_iron_ingot": "2022-09-19 14:31:29 +0000"
    },
    "done": true
  },
  "minecraft:recipes/redstone/piston": {
    "criteria": {
      "has_redstone": "2022-08-21 18:33:30 +0000"
    },
    "done": true
  },
  "minecraft:recipes/combat/shield": {
    "criteria": {
      "has_iron_ingot": "2022-09-19 14:31:29 +0000"
    },
    "done": true
  },
  "minecraft:recipes/decorations/lantern": {
    "criteria": {
      "has_iron_ingot": "2022-09-19 14:31:29 +0000"
    },
    "done": true
  },
  "minecraft:recipes/misc/bucket": {
    "criteria": {
      "has_iron_ingot": "2022-09-19 14:31:29 +0000"
    },
    "done": true
  },
  "minecraft:recipes/combat/iron_boots": {
    "criteria": {
      "has_iron_ingot": "2022-09-19 14:31:29 +0000"
    },
    "done": true
  },
  "minecraft:recipes/redstone/hopper": {
    "criteria": {
      "has_iron_ingot": "2022-09-19 14:31:29 +0000"
    },
    "done": true
  },
  "minecraft:recipes/building_blocks/black_concrete_powder": {
    "criteria": {
      "has_sand": "2022-09-23 21:23:53 +0000"
    },
    "done": true
  },
  "minecraft:recipes/decorations/chain": {
    "criteria": {
      "has_iron_ingot": "2022-09-19 14:31:29 +0000"
    },
    "done": true
  },
  "minecraft:recipes/redstone/note_block": {
    "criteria": {
      "has_redstone": "2022-08-21 18:33:30 +0000"
    },
    "done": true
  },
  "minecraft:recipes/redstone/dropper": {
    "criteria": {
      "has_redstone": "2022-08-21 18:33:30 +0000"
    },
    "done": true
  },
  "minecraft:recipes/combat/iron_chestplate": {
    "criteria": {
      "has_iron_ingot": "2022-09-19 14:31:29 +0000"
    },
    "done": true
  },
  "minecraft:recipes/combat/crossbow": {
    "criteria": {
      "has_iron_ingot": "2022-09-19 14:31:29 +0000"
    },
    "done": true
  },
  "minecraft:story/smelt_iron": {
    "criteria": {
      "iron": "2022-09-19 14:31:29 +0000"
    },
    "done": true
  },
  "minecraft:recipes/building_blocks/light_gray_concrete_powder": {
    "criteria": {
      "has_sand": "2022-09-23 21:23:53 +0000"
    },
    "done": true
  },
  "minecraft:recipes/building_blocks/light_blue_concrete_powder": {
    "criteria": {
      "has_sand": "2022-09-23 21:23:53 +0000"
    },
    "done": true
  },
  "minecraft:recipes/building_blocks/orange_concrete_powder": {
    "criteria": {
      "has_sand": "2022-09-23 21:23:53 +0000"
    },
    "done": true
  },
  "minecraft:recipes/building_blocks/cyan_concrete_powder": {
    "criteria": {
      "has_sand": "2022-09-23 21:23:53 +0000"
    },
    "done": true
  },
  "minecraft:recipes/building_blocks/glass": {
    "criteria": {
      "has_sand": "2022-09-23 21:23:53 +0000"
    },
    "done": true
  },
  "minecraft:recipes/combat/iron_helmet": {
    "criteria": {
      "has_iron_ingot": "2022-09-19 14:31:29 +0000"
    },
    "done": true
  },
  "DataVersion": 3120
}